autovenv/__init__.py
autovenv/command.py
autovenv/util.py
autovenv/virtualenvs.py
autovenv/python-build/LICENSE
autovenv/python-build/autovenv-python-build
autovenv/python-build/share/python-build/2.1.3
autovenv/python-build/share/python-build/2.2.3
autovenv/python-build/share/python-build/2.3.7
autovenv/python-build/share/python-build/2.4.0
autovenv/python-build/share/python-build/2.4.1
autovenv/python-build/share/python-build/2.4.2
autovenv/python-build/share/python-build/2.4.3
autovenv/python-build/share/python-build/2.4.4
autovenv/python-build/share/python-build/2.4.5
autovenv/python-build/share/python-build/2.4.6
autovenv/python-build/share/python-build/2.5.0
autovenv/python-build/share/python-build/2.5.1
autovenv/python-build/share/python-build/2.5.2
autovenv/python-build/share/python-build/2.5.3
autovenv/python-build/share/python-build/2.5.4
autovenv/python-build/share/python-build/2.5.5
autovenv/python-build/share/python-build/2.5.6
autovenv/python-build/share/python-build/2.6.0
autovenv/python-build/share/python-build/2.6.1
autovenv/python-build/share/python-build/2.6.2
autovenv/python-build/share/python-build/2.6.3
autovenv/python-build/share/python-build/2.6.4
autovenv/python-build/share/python-build/2.6.5
autovenv/python-build/share/python-build/2.6.6
autovenv/python-build/share/python-build/2.6.7
autovenv/python-build/share/python-build/2.6.8
autovenv/python-build/share/python-build/2.6.9
autovenv/python-build/share/python-build/2.7-dev
autovenv/python-build/share/python-build/2.7.0
autovenv/python-build/share/python-build/2.7.1
autovenv/python-build/share/python-build/2.7.10
autovenv/python-build/share/python-build/2.7.11
autovenv/python-build/share/python-build/2.7.12
autovenv/python-build/share/python-build/2.7.13
autovenv/python-build/share/python-build/2.7.14
autovenv/python-build/share/python-build/2.7.15
autovenv/python-build/share/python-build/2.7.16
autovenv/python-build/share/python-build/2.7.17
autovenv/python-build/share/python-build/2.7.18
autovenv-0.3.1671337561.dist-info/LICENSE
autovenv-0.3.1671337561.dist-info/METADATA
autovenv-0.3.1671337561.dist-info/WHEEL
autovenv-0.3.1671337561.dist-info/entry_points.txt
autovenv-0.3.1671337561.dist-info/top_level.txt
autovenv-0.3.1671337561.dist-info/RECORD
