Metadata-Version: 2.1
Name: autovenv
Version: 0.3.1671337561
Summary: virtualenv with less hassle
Home-page: http://autovenv.readthedocs.org
Author: Robert Lechte
Author-email: robertlechte@gmail.com
Classifier: Development Status :: 3 - Alpha
License-File: LICENSE
Requires-Dist: virtualenv
Requires-Dist: appdirs
Requires-Dist: pyyaml
